[
  {
    "sysdate": "2026-06-17 10:30",
    "regions": [
      {
        "region": "桃園",
        "avgScore": 106.6,
        "n": 2
      },
      {
        "region": "台南",
        "avgScore": 84.1,
        "n": 2
      },
      {
        "region": "高雄",
        "avgScore": 66.5,
        "n": 4
      },
      {
        "region": "花蓮",
        "avgScore": 37.8,
        "n": 1
      },
      {
        "region": "新北",
        "avgScore": 36.5,
        "n": 8
      },
      {
        "region": "台北",
        "avgScore": 28.1,
        "n": 11
      },
      {
        "region": "宜蘭",
        "avgScore": 26.2,
        "n": 2
      },
      {
        "region": "基隆",
        "avgScore": 23.8,
        "n": 1
      },
      {
        "region": "屏東",
        "avgScore": 19.5,
        "n": 1
      },
      {
        "region": "嘉義",
        "avgScore": 18.8,
        "n": 3
      },
      {
        "region": "雲林",
        "avgScore": 15,
        "n": 1
      },
      {
        "region": "台中",
        "avgScore": 12.8,
        "n": 8
      },
      {
        "region": "新竹",
        "avgScore": 9.8,
        "n": 4
      },
      {
        "region": "苗栗",
        "avgScore": 9,
        "n": 2
      },
      {
        "region": "彰化",
        "avgScore": 8,
        "n": 3
      },
      {
        "region": "台東",
        "avgScore": 6.3,
        "n": 1
      },
      {
        "region": "南投",
        "avgScore": 0,
        "n": 1
      }
    ]
  },
  {
    "sysdate": "2026-06-17 11:15",
    "regions": [
      {
        "region": "桃園",
        "avgScore": 88.5,
        "n": 2
      },
      {
        "region": "台南",
        "avgScore": 88,
        "n": 2
      },
      {
        "region": "高雄",
        "avgScore": 50,
        "n": 4
      },
      {
        "region": "新北",
        "avgScore": 34.3,
        "n": 8
      },
      {
        "region": "台北",
        "avgScore": 28.7,
        "n": 11
      },
      {
        "region": "花蓮",
        "avgScore": 26,
        "n": 1
      },
      {
        "region": "屏東",
        "avgScore": 21,
        "n": 1
      },
      {
        "region": "嘉義",
        "avgScore": 20,
        "n": 3
      },
      {
        "region": "宜蘭",
        "avgScore": 17,
        "n": 2
      },
      {
        "region": "基隆",
        "avgScore": 17,
        "n": 1
      },
      {
        "region": "台中",
        "avgScore": 14.6,
        "n": 8
      },
      {
        "region": "新竹",
        "avgScore": 13,
        "n": 4
      },
      {
        "region": "雲林",
        "avgScore": 13,
        "n": 1
      },
      {
        "region": "苗栗",
        "avgScore": 10,
        "n": 2
      },
      {
        "region": "台東",
        "avgScore": 9,
        "n": 1
      },
      {
        "region": "彰化",
        "avgScore": 8.3,
        "n": 3
      },
      {
        "region": "南投",
        "avgScore": 2,
        "n": 1
      }
    ]
  },
  {
    "sysdate": "2026-06-17 12:30",
    "regions": [
      {
        "region": "桃園",
        "avgScore": 86,
        "n": 2
      },
      {
        "region": "台南",
        "avgScore": 70.5,
        "n": 2
      },
      {
        "region": "高雄",
        "avgScore": 42.5,
        "n": 4
      },
      {
        "region": "新北",
        "avgScore": 33.5,
        "n": 8
      },
      {
        "region": "台北",
        "avgScore": 29.4,
        "n": 11
      },
      {
        "region": "基隆",
        "avgScore": 24,
        "n": 1
      },
      {
        "region": "花蓮",
        "avgScore": 24,
        "n": 1
      },
      {
        "region": "屏東",
        "avgScore": 23,
        "n": 1
      },
      {
        "region": "嘉義",
        "avgScore": 18.3,
        "n": 3
      },
      {
        "region": "宜蘭",
        "avgScore": 16.5,
        "n": 2
      },
      {
        "region": "台中",
        "avgScore": 13.9,
        "n": 8
      },
      {
        "region": "新竹",
        "avgScore": 12.5,
        "n": 4
      },
      {
        "region": "彰化",
        "avgScore": 8,
        "n": 3
      },
      {
        "region": "台東",
        "avgScore": 8,
        "n": 1
      },
      {
        "region": "苗栗",
        "avgScore": 7.5,
        "n": 2
      },
      {
        "region": "雲林",
        "avgScore": 7,
        "n": 1
      },
      {
        "region": "南投",
        "avgScore": 0,
        "n": 1
      }
    ]
  },
  {
    "sysdate": "2026-06-17 17:00",
    "regions": [
      {
        "region": "桃園",
        "avgScore": 75.5,
        "n": 2
      },
      {
        "region": "台南",
        "avgScore": 45.5,
        "n": 2
      },
      {
        "region": "高雄",
        "avgScore": 43,
        "n": 4
      },
      {
        "region": "新北",
        "avgScore": 30.5,
        "n": 8
      },
      {
        "region": "台北",
        "avgScore": 24.4,
        "n": 11
      },
      {
        "region": "屏東",
        "avgScore": 22,
        "n": 1
      },
      {
        "region": "花蓮",
        "avgScore": 18,
        "n": 1
      },
      {
        "region": "宜蘭",
        "avgScore": 17,
        "n": 2
      },
      {
        "region": "嘉義",
        "avgScore": 14.3,
        "n": 3
      },
      {
        "region": "基隆",
        "avgScore": 13,
        "n": 1
      },
      {
        "region": "台中",
        "avgScore": 11.9,
        "n": 8
      },
      {
        "region": "彰化",
        "avgScore": 9.7,
        "n": 3
      },
      {
        "region": "新竹",
        "avgScore": 9.3,
        "n": 4
      },
      {
        "region": "雲林",
        "avgScore": 9,
        "n": 1
      },
      {
        "region": "台東",
        "avgScore": 8,
        "n": 1
      },
      {
        "region": "苗栗",
        "avgScore": 5,
        "n": 2
      },
      {
        "region": "南投",
        "avgScore": 2,
        "n": 1
      }
    ]
  },
  {
    "sysdate": "2026-06-17 21:45",
    "regions": [
      {
        "region": "桃園",
        "avgScore": 61,
        "n": 2
      },
      {
        "region": "台南",
        "avgScore": 57,
        "n": 2
      },
      {
        "region": "高雄",
        "avgScore": 41.5,
        "n": 4
      },
      {
        "region": "新北",
        "avgScore": 33.6,
        "n": 8
      },
      {
        "region": "台北",
        "avgScore": 24.7,
        "n": 11
      },
      {
        "region": "花蓮",
        "avgScore": 23,
        "n": 1
      },
      {
        "region": "屏東",
        "avgScore": 18,
        "n": 1
      },
      {
        "region": "宜蘭",
        "avgScore": 17,
        "n": 2
      },
      {
        "region": "嘉義",
        "avgScore": 15.7,
        "n": 3
      },
      {
        "region": "彰化",
        "avgScore": 14.3,
        "n": 3
      },
      {
        "region": "雲林",
        "avgScore": 14,
        "n": 1
      },
      {
        "region": "台東",
        "avgScore": 14,
        "n": 1
      },
      {
        "region": "基隆",
        "avgScore": 13,
        "n": 1
      },
      {
        "region": "台中",
        "avgScore": 12.3,
        "n": 8
      },
      {
        "region": "新竹",
        "avgScore": 10.3,
        "n": 4
      },
      {
        "region": "苗栗",
        "avgScore": 6.5,
        "n": 2
      },
      {
        "region": "南投",
        "avgScore": 2,
        "n": 1
      }
    ]
  },
  {
    "sysdate": "2026-06-18 01:15",
    "regions": [
      {
        "region": "桃園",
        "avgScore": 64.5,
        "n": 2
      },
      {
        "region": "台南",
        "avgScore": 59.5,
        "n": 2
      },
      {
        "region": "高雄",
        "avgScore": 47.3,
        "n": 4
      },
      {
        "region": "新北",
        "avgScore": 32,
        "n": 8
      },
      {
        "region": "花蓮",
        "avgScore": 26,
        "n": 1
      },
      {
        "region": "台北",
        "avgScore": 24.8,
        "n": 11
      },
      {
        "region": "宜蘭",
        "avgScore": 20,
        "n": 2
      },
      {
        "region": "屏東",
        "avgScore": 20,
        "n": 1
      },
      {
        "region": "雲林",
        "avgScore": 18,
        "n": 1
      },
      {
        "region": "嘉義",
        "avgScore": 14,
        "n": 3
      },
      {
        "region": "台中",
        "avgScore": 12.5,
        "n": 8
      },
      {
        "region": "彰化",
        "avgScore": 12.3,
        "n": 3
      },
      {
        "region": "基隆",
        "avgScore": 10,
        "n": 1
      },
      {
        "region": "新竹",
        "avgScore": 8.3,
        "n": 4
      },
      {
        "region": "苗栗",
        "avgScore": 5,
        "n": 2
      },
      {
        "region": "台東",
        "avgScore": 4,
        "n": 1
      },
      {
        "region": "南投",
        "avgScore": 1,
        "n": 1
      }
    ]
  },
  {
    "sysdate": "2026-06-18 04:15",
    "regions": [
      {
        "region": "桃園",
        "avgScore": 64,
        "n": 2
      },
      {
        "region": "台南",
        "avgScore": 60.5,
        "n": 2
      },
      {
        "region": "高雄",
        "avgScore": 49.5,
        "n": 4
      },
      {
        "region": "新北",
        "avgScore": 31.4,
        "n": 8
      },
      {
        "region": "花蓮",
        "avgScore": 26,
        "n": 1
      },
      {
        "region": "台北",
        "avgScore": 23.8,
        "n": 11
      },
      {
        "region": "宜蘭",
        "avgScore": 21.5,
        "n": 2
      },
      {
        "region": "屏東",
        "avgScore": 21,
        "n": 1
      },
      {
        "region": "雲林",
        "avgScore": 18,
        "n": 1
      },
      {
        "region": "彰化",
        "avgScore": 14,
        "n": 3
      },
      {
        "region": "嘉義",
        "avgScore": 13.7,
        "n": 3
      },
      {
        "region": "台中",
        "avgScore": 13.1,
        "n": 8
      },
      {
        "region": "基隆",
        "avgScore": 8,
        "n": 1
      },
      {
        "region": "新竹",
        "avgScore": 8,
        "n": 4
      },
      {
        "region": "苗栗",
        "avgScore": 5.5,
        "n": 2
      },
      {
        "region": "台東",
        "avgScore": 4,
        "n": 1
      },
      {
        "region": "南投",
        "avgScore": 0,
        "n": 1
      }
    ]
  },
  {
    "sysdate": "2026-06-18 06:45",
    "regions": [
      {
        "region": "桃園",
        "avgScore": 66,
        "n": 2
      },
      {
        "region": "台南",
        "avgScore": 59,
        "n": 2
      },
      {
        "region": "高雄",
        "avgScore": 49.3,
        "n": 4
      },
      {
        "region": "新北",
        "avgScore": 30.8,
        "n": 8
      },
      {
        "region": "花蓮",
        "avgScore": 28,
        "n": 1
      },
      {
        "region": "台北",
        "avgScore": 24,
        "n": 11
      },
      {
        "region": "宜蘭",
        "avgScore": 21,
        "n": 2
      },
      {
        "region": "屏東",
        "avgScore": 21,
        "n": 1
      },
      {
        "region": "雲林",
        "avgScore": 19,
        "n": 1
      },
      {
        "region": "嘉義",
        "avgScore": 14.7,
        "n": 3
      },
      {
        "region": "彰化",
        "avgScore": 14,
        "n": 3
      },
      {
        "region": "台中",
        "avgScore": 13,
        "n": 8
      },
      {
        "region": "基隆",
        "avgScore": 11,
        "n": 1
      },
      {
        "region": "新竹",
        "avgScore": 8.5,
        "n": 4
      },
      {
        "region": "苗栗",
        "avgScore": 5.5,
        "n": 2
      },
      {
        "region": "台東",
        "avgScore": 4,
        "n": 1
      },
      {
        "region": "南投",
        "avgScore": 0,
        "n": 1
      }
    ]
  }
]